json_deserializer/__init__.py
json_deserializer-0.0.7.dist-info/LICENSE
json_deserializer-0.0.7.dist-info/METADATA
json_deserializer-0.0.7.dist-info/WHEEL
json_deserializer-0.0.7.dist-info/top_level.txt
json_deserializer-0.0.7.dist-info/RECORD
