Metadata-Version: 2.1
Name: json-deserializer
Version: 0.0.7
Summary: Attempts to correctly deserialize objects that json decoder cannot.
Home-page: https://github.com/mathewmoon/json-deserializer
Author: Mathew Moon
Author-email: me@mathewmoon.net
License: Apache 2.0
Platform: UNKNOWN
Classifier: Development Status :: 5 - Production/Stable
Classifier: Intended Audience :: Developers
Classifier: License :: OSI Approved :: Apache Software License
Classifier: Programming Language :: Python :: 3.7
License-File: LICENSE
